comprehend/layers.py
comprehend/utils.py
comprehend-0.0.8.dist-info/METADATA
comprehend-0.0.8.dist-info/WHEEL
comprehend-0.0.8.dist-info/top_level.txt
comprehend-0.0.8.dist-info/RECORD
