Metadata-Version: 2.1
Name: comprehend
Version: 0.0.8
Summary: Compress, Predict, Enhance, and Denoise
Author-email: Dan Jacobellis <danjacobellis@utexas.edu>
Classifier: Programming Language :: Python :: 3
Classifier: Operating System :: OS Independent
Requires-Python: >=3.6
Requires-Dist: torch
